AUTHORS
ChangeLog
LICENSE
README.rst
example.conf
requirements.txt
setup.cfg
setup.py
test-requirements.txt
tox.ini
ahc_tools/__init__.py
ahc_tools/conf.py
ahc_tools/exc.py
ahc_tools/match.py
ahc_tools/report.py
ahc_tools/utils.py
ahc_tools.egg-info/PKG-INFO
ahc_tools.egg-info/SOURCES.txt
ahc_tools.egg-info/dependency_links.txt
ahc_tools.egg-info/entry_points.txt
ahc_tools.egg-info/not-zip-safe
ahc_tools.egg-info/pbr.json
ahc_tools.egg-info/requires.txt
ahc_tools.egg-info/top_level.txt
ahc_tools/common/__init__.py
ahc_tools/common/swift.py
ahc_tools/test/__init__.py
ahc_tools/test/base.py
ahc_tools/test/test_match.py
ahc_tools/test/test_report.py
ahc_tools/test/test_swift.py
ahc_tools/test/test_utils.py